.coveragerc
.travis.yml
LICENSE
MANIFEST.in
README.rst
setup.cfg
setup.py
tox.ini
Mopidy_Touchscreen.egg-info/PKG-INFO
Mopidy_Touchscreen.egg-info/SOURCES.txt
Mopidy_Touchscreen.egg-info/dependency_links.txt
Mopidy_Touchscreen.egg-info/entry_points.txt
Mopidy_Touchscreen.egg-info/not-zip-safe
Mopidy_Touchscreen.egg-info/requires.txt
Mopidy_Touchscreen.egg-info/top_level.txt
mopidy_touchscreen/__init__.py
mopidy_touchscreen/ext.conf
mopidy_touchscreen/icomoon.ttf
mopidy_touchscreen/screen_manager.py
mopidy_touchscreen/touch_screen.py
mopidy_touchscreen/graphic_utils/__init__.py
mopidy_touchscreen/graphic_utils/background_manager.py
mopidy_touchscreen/graphic_utils/list_view.py
mopidy_touchscreen/graphic_utils/screen_objects.py
mopidy_touchscreen/input/__init__.py
mopidy_touchscreen/input/gpio_inpput_manager.py
mopidy_touchscreen/input/input_manager.py
mopidy_touchscreen/screens/__init__.py
mopidy_touchscreen/screens/base_screen.py
mopidy_touchscreen/screens/keyboard_screen.py
mopidy_touchscreen/screens/library_screen.py
mopidy_touchscreen/screens/main_screen.py
mopidy_touchscreen/screens/menu_screen.py
mopidy_touchscreen/screens/playlist_screen.py
mopidy_touchscreen/screens/search_screen.py
mopidy_touchscreen/screens/tracklist.py
tests/__init__.py
tests/test_extension.py