Metadata-Version: 1.1
Name: Mopidy-Touchscreen
Version: 1.0.0
Summary: Mopidy extension to show info on a display and control from it
Home-page: https://github.com/9and3r/mopidy-touchscreen
Author: 9and3r
Author-email: 9and3r@gmail.com
License: Apache License, Version 2.0
Platform: UNKNOWN
Classifier: Environment :: No Input/Output (Daemon)
Classifier: Intended Audience :: End Users/Desktop
Classifier: License :: OSI Approved :: Apache Software License
Classifier: Operating System :: OS Independent
Classifier: Programming Language :: Python :: 2
Classifier: Topic :: Multimedia :: Sound/Audio :: Players
